pymdo/__init__.py
pymdo/core/__init__.py
pymdo/core/cache.py
pymdo/core/derivative_assembler.py
pymdo/core/discipline.py
pymdo/core/tools.py
pymdo/core/variable.py
pymdo/mda/__init__.py
pymdo/mda/factory.py
pymdo/mda/gauss_seidel.py
pymdo/mda/hybrid.py
pymdo/mda/jacobi.py
pymdo/mda/mda.py
pymdo/mda/newton.py
pymdo/mda/smart_mda.py
pymdo/mdo/__init__.py
pymdo/mdo/mdf.py
pymdo/mdo/mdo.py
pymdo-0.0.7.dist-info/LICENSE.txt
pymdo-0.0.7.dist-info/METADATA
pymdo-0.0.7.dist-info/WHEEL
pymdo-0.0.7.dist-info/top_level.txt
pymdo-0.0.7.dist-info/RECORD
