Metadata-Version: 2.1
Name: pymdo
Version: 0.0.7
Summary: A lightweight package for Multidisciplinary Analysis and Optimization
Author: Dimitrios Pallas
Author-email: mc19054@mail.ntua.gr
License: MIT License
Keywords: Optimization,MDO,Multidisciplinary Analysis and Optimization
Classifier: Programming Language :: Python :: 3
Classifier: License :: OSI Approved :: MIT License
Classifier: Operating System :: OS Independent
Requires-Python: >=3.8
License-File: LICENSE.txt
Requires-Dist: numpy
Requires-Dist: scipy
Requires-Dist: networkx
Requires-Dist: h5py
Requires-Dist: matplotlib
